llm_jina_api.py
llm_jina_api-0.1a0.dist-info/LICENSE
llm_jina_api-0.1a0.dist-info/METADATA
llm_jina_api-0.1a0.dist-info/WHEEL
llm_jina_api-0.1a0.dist-info/entry_points.txt
llm_jina_api-0.1a0.dist-info/top_level.txt
llm_jina_api-0.1a0.dist-info/RECORD
