Metadata-Version: 2.1
Name: llm-jina-api
Version: 0.1a0
Summary: Access Jina AI embeddings via their API
Author: Simon Willison
License: Apache-2.0
Project-URL: Homepage, https://github.com/simonw/llm-jina-api
Project-URL: Changelog, https://github.com/simonw/llm-jina-api/releases
Project-URL: Issues, https://github.com/simonw/llm-jina-api/issues
Project-URL: CI, https://github.com/simonw/llm-jina-api/actions
Classifier: License :: OSI Approved :: Apache Software License
License-File: LICENSE
Requires-Dist: llm
Requires-Dist: pillow
Provides-Extra: test
Requires-Dist: pytest ; extra == 'test'
